pgwasm/__init__.py
pgwasm/converters.py
pgwasm/core.py
pgwasm/dbapi.py
pgwasm/exceptions.py
pgwasm-0.2.0.dist-info/LICENSE
pgwasm-0.2.0.dist-info/WHEEL
pgwasm-0.2.0.dist-info/METADATA
pgwasm-0.2.0.dist-info/RECORD
